asro_nlp/__init__.py
asro_nlp/asro_nlp.py
asro_nlp/data/kamus_negative.xlsx
asro_nlp/data/kamus_positive.xlsx
asro_nlp/data/kamuskatabaku.xlsx
asro_nlp/data/kata-dasar.original.txt
asro_nlp/data/kata-dasar.txt
asro_nlp/data/news_dictionary.txt
asro_nlp/data/stopwords.txt
asronlp-0.1.20.dist-info/LICENSE
asronlp-0.1.20.dist-info/METADATA
asronlp-0.1.20.dist-info/WHEEL
asronlp-0.1.20.dist-info/top_level.txt
asronlp-0.1.20.dist-info/RECORD
